pyutil/__init__.py
pyutil/message.py
pyutil/parent.py
pyutil/config/__init__.py
pyutil/config/folder.py
pyutil/config/logging.py
pyutil/config/random.py
pyutil/config/yaml.py
pyutil/cvx/__init__.py
pyutil/cvx/util.py
pyutil/mongo/__init__.py
pyutil/mongo/engine/__init__.py
pyutil/mongo/engine/strategy.py
pyutil/mongo/engine/symbol.py
pyutil/performance/__init__.py
pyutil/performance/adjust.py
pyutil/performance/drawdown.py
pyutil/performance/month.py
pyutil/performance/periods.py
pyutil/performance/return_series.py
pyutil/performance/var.py
pyutil/portfolio/__init__.py
pyutil/portfolio/analysis.py
pyutil/portfolio/format.py
pyutil/portfolio/portfolio.py
pyutil/strategy/__init__.py
pyutil/strategy/config.py
pyutil/timeseries/__init__.py
pyutil/timeseries/merge.py
pyutil/timeseries/signal.py
lob_pyutil-5.2.1.dist-info/LICENSE.txt
lob_pyutil-5.2.1.dist-info/METADATA
lob_pyutil-5.2.1.dist-info/WHEEL
lob_pyutil-5.2.1.dist-info/top_level.txt
lob_pyutil-5.2.1.dist-info/RECORD
