Metadata-Version: 2.1
Name: lob-pyutil
Version: 5.2.1
Summary: Utility code for a Swiss Family Office
Home-page: https://github.com/lobnek/pyutil
Author: Thomas Schmelzer
Author-email: thomas.schmelzer@gmail.com
License: MIT
Platform: UNKNOWN
Requires-Dist: requests (>=2.23.0)
Requires-Dist: pandas (>=1.0.5)
Requires-Dist: pyyaml (>=5.3.1)
Requires-Dist: antarctic (>=0.3.1)
